medim/__init__.py
medim/models/__init__.py
medim/models/_factory.py
medim/models/_hf_utils.py
medim/models/_pretrain.py
medim/models/_registry.py
medim/models/sam_med3d.py
medim/models/stu_net.py
medim-0.1.2.dist-info/licenses/LICENSE
medim-0.1.2.dist-info/METADATA
medim-0.1.2.dist-info/WHEEL
medim-0.1.2.dist-info/top_level.txt
medim-0.1.2.dist-info/RECORD
