Metadata-Version: 2.4
Name: medim
Version: 0.1.2
Summary: MedIM is a all-in-one collection for Medical Image Models in PyTorch Style.
Author-email: Haoyu Wang <small_dark@sina.com>
License:                                  Apache License
Project-URL: Homepage, https://github.com/uni-medical/Pytorch-Medical-Image-Models
Requires-Python: >=3.9
License-File: LICENSE
Requires-Dist: appdirs
Requires-Dist: numpy
Requires-Dist: torch>=2.4.0
Requires-Dist: einops
Requires-Dist: huggingface_hub
Requires-Dist: pytest
Dynamic: license-file
